{
  "title": "Portfolio",
  "author": "Sintu Boro",
  "headerTitle": "",
  "description": "I write about exciting technologies, development and best practices at large.",
  "language": "en-us",
  "siteUrl": "https://sboro.vercel.app",
  "siteRepo": "https://github.com/Boro23-wq/boroportfolio-v4",
  "image": "/static/images/avatar.png",
  "socialBanner": "/static/images/social-card.png",
  "email": "sboro2899@gmail.com",
  "github": "https://github.com/Boro23-wq",
  "twitter": "https://twitter.com/23boroz",
  "facebook": "",
  "youtube": "",
  "linkedin": "https://www.linkedin.com/in/sintu-boro/",
  "locale": "en-US"
}
